_vaststream_pybind11.cpython-38-x86_64-linux-gnu.so
vaststream/__init__.py
vaststream/vace/__init__.py
vaststream/vace/common.py
vaststream/vace/op_attr_desc.py
vaststream/vace/op_base.py
vaststream/vace/op_custom.py
vaststream/vace/op_fusion.py
vaststream/vace/op_fusion_wrapper.py
vaststream/vace/op_single.py
vaststream/vace/utils.py
vaststream/vace/vace_custom_op_example.py
vaststream/vacl/__init__.py
vaststream/vacl/common.py
vaststream/vacl/model.py
vaststream/vacl/stream.py
vaststream/vacl/utils.py
vaststream/vacm/__init__.py
vaststream/vacm/basic.py
vaststream/vacm/common.py
vaststream/vacm/context.py
vaststream/vacm/databuffer.py
vaststream/vacm/dataset.py
vaststream/vacm/device.py
vaststream/vacm/env.py
vaststream/vacm/log.py
vaststream/vacm/memory.py
vaststream/vacm/os.py
vaststream/vacm/tensor.py
vaststream/vacm/utility.py
vaststream/vacm/utils.py
vaststream/vame/__init__.py
vaststream/vame/common.py
vaststream/vame/decoder.py
vaststream/vame/encoder.py
vaststream/vame/utils.py
vaststream/vaml/__init__.py
vaststream/vaml/base.py
vaststream/vaml/callbackfunc.py
vaststream/vaml/card.py
vaststream/vaml/device.py
vaststream/vaml/die.py
vaststream/vaml/log.py
vaststream/vaml/profiler.py
vaststream/vaml/statis.py
vaststream/vaml/utils.py
vaststream_ai-1.0.0.dist-info/METADATA
vaststream_ai-1.0.0.dist-info/WHEEL
vaststream_ai-1.0.0.dist-info/top_level.txt
vaststream_ai-1.0.0.dist-info/RECORD
